{
  "timestamp": "2025-08-26T21:36:48.975557",
  "ticker": "SPY",
  "data_points": 4992,
  "latest_signal": {
    "date": "2025-08-26",
    "signal": "HOLD",
    "position": "FLAT",
    "phase_quadrant": "Quadrante 3 (Picco -> Discesa)",
    "phase_value": 1.192909144916396,
    "oscillator_value": 10.010999999999967,
    "signal_strength": 50.28588382524043,
    "confidence": "MEDIUM",
    "price": 645.16,
    "timestamp": "2025-08-26T21:36:47.145062"
  },
  "backtest_metrics": {
    "total_return_%": 157.73160209553217,
    "max_drawdown_%": 1.8781794555555966,
    "sharpe_ratio": 1.2234108703760578,
    "sortino_ratio": 1.5114757768797331,
    "calmar_ratio": 8.931925497209944,
    "total_trades": 27,
    "win_rate_%": 77.77777777777779,
    "profit_factor": 20.51436357326666
  },
  "cycle_analysis": {
    "dominant_period": 84.0,
    "p_value": 0.0,
    "significant": "True"
  }
}